gridcode/__init__.py
gridcode/__main__.py
gridcode/agents/__init__.py
gridcode/agents/aggregator.py
gridcode/agents/base.py
gridcode/agents/explore.py
gridcode/agents/message_bus.py
gridcode/agents/plan.py
gridcode/agents/pool.py
gridcode/agents/review.py
gridcode/agents/test_runner.py
gridcode/agents/documentation/__init__.py
gridcode/agents/documentation/api_documenter.py
gridcode/agents/documentation/base.py
gridcode/agents/documentation/docs_architect.py
gridcode/agents/documentation/tutorial_engineer.py
gridcode/agents/experts/__init__.py
gridcode/agents/experts/architect.py
gridcode/agents/experts/code_reviewer.py
gridcode/agents/experts/debugger.py
gridcode/cli/__init__.py
gridcode/cli/__main__.py
gridcode/cli/config.py
gridcode/cli/interactive.py
gridcode/cli/main.py
gridcode/cli/plugins.py
gridcode/cli/run.py
gridcode/config/__init__.py
gridcode/config/discovery.py
gridcode/config/loader.py
gridcode/config/models.py
gridcode/config/templates.py
gridcode/config/validator.py
gridcode/core/__init__.py
gridcode/core/context.py
gridcode/core/runtime.py
gridcode/interaction/__init__.py
gridcode/interaction/base.py
gridcode/interaction/console.py
gridcode/interaction/mock.py
gridcode/mcp/__init__.py
gridcode/mcp/client.py
gridcode/mcp/pool.py
gridcode/mcp/transports.py
gridcode/nexus/__init__.py
gridcode/nexus/base.py
gridcode/nexus/langgraph.py
gridcode/nexus/pydantic_ai.py
gridcode/nexus/tool_converter.py
gridcode/nexus/types.py
gridcode/plugins/__init__.py
gridcode/plugins/base.py
gridcode/plugins/discovery.py
gridcode/plugins/examples.py
gridcode/plugins/hooks.py
gridcode/plugins/mcp.py
gridcode/prompts/__init__.py
gridcode/prompts/composer.py
gridcode/prompts/reminder_injector.py
gridcode/prompts/template.py
gridcode/prompts/tool_result_enhancer.py
gridcode/prompts/variable_resolver.py
gridcode/prompts/reminders/__init__.py
gridcode/prompts/reminders/base.py
gridcode/prompts/reminders/context_reminders.py
gridcode/prompts/reminders/file_operations.py
gridcode_runtime-0.1.2.dist-info/licenses/LICENSE
gridcode_runtime-0.1.2.dist-info/METADATA
gridcode_runtime-0.1.2.dist-info/WHEEL
gridcode_runtime-0.1.2.dist-info/entry_points.txt
gridcode_runtime-0.1.2.dist-info/top_level.txt
gridcode_runtime-0.1.2.dist-info/RECORD
