Metadata-Version: 2.4
Name: gridcode-runtime
Version: 0.1.2
Summary: Build production AI agents with modular architecture, advanced prompt engineering, and framework-agnostic design (LangGraph/Pydantic-AI)
Author: GridCode Team
License: MIT
Project-URL: Homepage, https://github.com/gridcode/gridcode-runtime
Project-URL: Documentation, https://github.com/gridcode/gridcode-runtime/docs
Project-URL: Repository, https://github.com/gridcode/gridcode-runtime
Project-URL: Issues, https://github.com/gridcode/gridcode-runtime/issues
Keywords: agent,ai,llm,langgraph,pydantic-ai
Classifier: Development Status :: 3 - Alpha
Classifier: Intended Audience :: Developers
Classifier: License :: OSI Approved :: MIT License
Classifier: Programming Language :: Python :: 3
Classifier: Programming Language :: Python :: 3.11
Classifier: Programming Language :: Python :: 3.12
Requires-Python: >=3.11
License-File: LICENSE
Requires-Dist: anthropic>=0.40.0
Requires-Dist: pydantic>=2.0.0
Requires-Dist: pyyaml>=6.0
Requires-Dist: loguru>=0.7.0
Requires-Dist: aiofiles>=23.0.0
Requires-Dist: aiosqlite>=0.20.0
Requires-Dist: typer>=0.12.0
Requires-Dist: rich>=13.0.0
Requires-Dist: python-dotenv>=1.0.0
Requires-Dist: prompt-toolkit>=3.0.0
Provides-Extra: langgraph
Requires-Dist: langgraph>=0.2.0; extra == "langgraph"
Requires-Dist: langchain-core>=0.3.0; extra == "langgraph"
Requires-Dist: langchain-anthropic>=0.2.0; extra == "langgraph"
Requires-Dist: langchain-openai>=0.2.0; extra == "langgraph"
Provides-Extra: pydantic-ai
Requires-Dist: pydantic-ai>=0.0.13; extra == "pydantic-ai"
Provides-Extra: dev
Requires-Dist: pytest>=8.0.0; extra == "dev"
Requires-Dist: pytest-asyncio>=0.23.0; extra == "dev"
Requires-Dist: pytest-cov>=4.1.0; extra == "dev"
Requires-Dist: black>=24.0.0; extra == "dev"
Requires-Dist: isort>=5.13.0; extra == "dev"
Requires-Dist: mypy>=1.8.0; extra == "dev"
Requires-Dist: ruff>=0.1.0; extra == "dev"
Provides-Extra: all
Requires-Dist: gridcode-runtime[dev,langgraph,pydantic-ai]; extra == "all"
Dynamic: license-file
